drf_enum_field/__init__.py
drf_enum_field/fields.py
drf_enum_field/serializers.py
drf_enum_field-0.9.3.dist-info/LICENSE.md
drf_enum_field-0.9.3.dist-info/METADATA
drf_enum_field-0.9.3.dist-info/WHEEL
drf_enum_field-0.9.3.dist-info/top_level.txt
drf_enum_field-0.9.3.dist-info/RECORD
