Metadata-Version: 1.1
Name: drf-enum-field
Version: 0.9.3
Summary: EnumField support for Django REST Framework 3
Home-page: https://github.com/seebass/drf-enum-field
Author: Sebastian Bredehöft
Author-email: bredehoeft.sebastian@gmail.com
License: MIT
Platform: UNKNOWN
Classifier: Development Status :: 4 - Beta
Classifier: Environment :: Web Environment
Classifier: Framework :: Django
Classifier: Intended Audience :: Developers
Classifier: License :: OSI Approved :: MIT License
Classifier: Operating System :: OS Independent
Classifier: Programming Language :: Python
Classifier: Programming Language :: Python :: 3
Classifier: Topic :: Internet :: WWW/HTTP
